latin_paradigm_finder/__init__.py
latin_paradigm_finder/__main__.py
latin_paradigm_finder-0.1.6.dist-info/LICENSE
latin_paradigm_finder-0.1.6.dist-info/METADATA
latin_paradigm_finder-0.1.6.dist-info/WHEEL
latin_paradigm_finder-0.1.6.dist-info/entry_points.txt
latin_paradigm_finder-0.1.6.dist-info/top_level.txt
latin_paradigm_finder-0.1.6.dist-info/RECORD
