Metadata-Version: 2.1
Name: latin-paradigm-finder
Version: 0.1.6
Summary: Find latin verbs and their paradigms present in text.
Home-page: https://github.com/bortox/latin-paradigm-finder
Author: Andrea Bortolotti / bortox
Author-email: borto@tuta.io
License: GPLv3
Platform: UNKNOWN
Classifier: License :: OSI Approved :: GNU General Public License v3 (GPLv3)
Classifier: Programming Language :: Python
Classifier: Programming Language :: Python :: 3
Classifier: Programming Language :: Python :: 3.6
Classifier: Programming Language :: Python :: Implementation :: PyPy
Requires-Python: >=3.6.0
Requires-Dist: aiohttp (==3.7.3)
Requires-Dist: beautifulsoup4 (==4.9.3)
Requires-Dist: clipboard (==0.0.4)
Requires-Dist: pathvalidate (==2.3.1)
Requires-Dist: questionary (==1.9.0)
Requires-Dist: termcolor (==1.1.0)
Requires-Dist: Unidecode (==1.1.2)
Requires-Dist: lxml (==4.6.2)
Requires-Dist: colorama (==0.4.4)
